main.py
mseep_mem0_mcp-0.1.8.dist-info/METADATA
mseep_mem0_mcp-0.1.8.dist-info/WHEEL
mseep_mem0_mcp-0.1.8.dist-info/entry_points.txt
mseep_mem0_mcp-0.1.8.dist-info/top_level.txt
mseep_mem0_mcp-0.1.8.dist-info/RECORD
