Metadata-Version: 2.4
Name: mseep-mem0-mcp
Version: 0.1.8
Summary: Add your description here
Author-email: mseep <support@skydeck.ai>
Requires-Python: >=3.12
Requires-Dist: httpx>=0.28.1
Requires-Dist: mcp[cli]>=1.3.0
Requires-Dist: mem0ai>=0.1.55
